{
    "name": "Igram Stats",
    "logo": {
        "Type": "Logo",
        "name": "IgramStatsLogo",
        "description": "Logo of Igram Stats featuring a radial chart design"
    },
    "sections": [
        {
            "title": "Welcome to Igram Stats",
            "subtitle": "Unlock Insights to Grow Your Instagram Presence",
            "name": "heroSection",
            "label": "Home",
            "content": "Explore the power of analytical insights and enhance your Instagram strategy with Igram Stats. Start your journey of growth today!",
            "order": 1,
            "Type": "Hero",
            "images": [
                {
                    "Type": "Background",
                    "name": "InstagramAnalytics",
                    "description": "Background image showcasing Instagram analytics dashboard"
                },
                {
                    "Type": "Hero",
                    "name": "MainBanner",
                    "description": "A vibrant image depicting a person analyzing Instagram stats on a laptop"
                }
            ]
        },
        {
            "title": "About Igram Stats",
            "subtitle": "Our Mission and Vision",
            "name": "aboutSection",
            "label": "About",
            "content": "At Igram Stats, our mission is to empower influencers, brands, and individuals with meaningful data insights to elevate their Instagram presence. We believe in transparency and simplicity, providing tools that transform numbers into actionable strategies.\n\n### Our Vision  \nTo become the go-to platform for Instagram analytics, offering a seamless and comprehensive understanding of your online presence through intuitive design and expert support.",
            "order": 2,
            "Type": "About",
            "images": [
                {
                    "Type": "Infographic",
                    "name": "MissionGraph",
                    "description": "Infographic illustrating the mission and vision of Igram Stats"
                }
            ]
        },
        {
            "title": "Our Services",
            "subtitle": "Comprehensive Instagram Analytics",
            "name": "servicesSection",
            "label": "Services",
            "content": "Unlock the full potential of your Instagram account with our premium analytics services:\n\n- **Follower Analytics**: Get detailed insights into your audience and how they interact with your content.\n- **Engagement Metrics**: Understand which posts drive the most engagement to optimize your content strategy.\n- **Hashtag Performance Tracking**: Discover the best hashtags to widen your reach and visibility.\n- **Competitor Analysis**: Stay ahead by benchmarking against your competitors' performance.\n- **Custom Reports**: Generate tailored reports to communicate your successes with stakeholders.",
            "order": 3,
            "Type": "Services",
            "images": [
                {
                    "Type": "ItemListing",
                    "name": "ServicePreview",
                    "description": "Images showing previews of different analytics services offered"
                }
            ]
        },
        {
            "title": "Testimonials",
            "subtitle": "Hear from Our Satisfied Users",
            "name": "testimonialsSection",
            "label": "Testimonials",
            "content": "Join thousands of happy users who have transformed their Instagram insight capacity:\n\n> \"Igram Stats has revolutionized how I plan my content strategy. The insights are incredibly accurate and easy to understand!\"  \n> \u2014 Alexia J., Social Media Manager\n\n> \"The competitor analysis feature gave me the edge I needed to outpace my competition!\"  \n> \u2014 James T., Influencer\n\n> \"Custom reports are a lifesaver for our monthly team meetings!\"  \n> \u2014 Natalie R., Marketing Director",
            "order": 4,
            "Type": "Testimonials",
            "images": [
                {
                    "Type": "Testimonial",
                    "name": "TestimonialsImage",
                    "description": "Collage of satisfied customers showcasing success stories"
                }
            ]
        },
        {
            "title": "Contact Us",
            "subtitle": "Get in Touch with Igram Stats",
            "name": "contactSection",
            "label": "Contact",
            "content": "Whether you have questions, feedback, or want to start a new project, reach out to us!\n\n- **Email**: support@igramstats.com  \n- **Phone**: +1 (800) 123-4567  \n- **Address**: 123 Analytics Drive, Suite 100, Analytics City, AC 12345\n\n**We\u2019re here to help you succeed!**",
            "order": 5,
            "Type": "Contact",
            "images": [
                {
                    "Type": "Map",
                    "name": "LocationMap",
                    "description": "Map showing the location of Igram Stats headquarters"
                }
            ]
        },
        {
            "title": "Stay Updated with Igram Stats",
            "subtitle": "Latest News and Updates",
            "name": "newsSection",
            "label": "News",
            "content": "### Announcement: \nWe're excited to introduce new features to our analytics dashboard including real-time hashtag tracking!\n\n### Blog Highlights: \n- **Top 10 Instagram Strategies for 2023**  \n- **The Power of Data: How Analytics Can Transform Your Social Media** \n",
            "order": 6,
            "Type": "News",
            "images": [
                {
                    "Type": "Promotional",
                    "name": "NewFeaturesPromo",
                    "description": "Promotional image highlighting new features of Igram Stats"
                }
            ]
        },
        {
            "title": "Meet the Igram Stats Team",
            "subtitle": "Get to Know Us",
            "name": "teamSection",
            "label": "Team",
            "content": "Our team comprises seasoned analysts, passionate marketers, and innovative developers all committed to empowering your Instagram growth. Meet the brilliant minds behind Igram Stats!\n\n- **Sara L.** - Chief Analytics Officer  \n- **Tom A.** - Product Manager  \n- **Lina K.** - Marketing Lead\n\nTogether, we bring years of expertise to deliver top-notch insights and tools for your Instagram success.",
            "order": 7,
            "Type": "Team",
            "images": [
                {
                    "Type": "Headshot",
                    "name": "SaraLHeadshot",
                    "description": "Headshot of Sara L."
                },
                {
                    "Type": "Headshot",
                    "name": "TomAHeadshot",
                    "description": "Headshot of Tom A."
                },
                {
                    "Type": "Headshot",
                    "name": "LinaKHeadshot",
                    "description": "Headshot of Lina K."
                }
            ]
        }
    ]
}